pydnstest/__init__.py
pydnstest/checks.py
pydnstest/config.py
pydnstest/dns.py
pydnstest/main.py
pydnstest/parser.py
pydnstest/util.py
pydnstest/version.py
pydnstest/tests/__init__.py
pydnstest/tests/dnstest_check_add_test.py
pydnstest/tests/dnstest_check_change_test.py
pydnstest/tests/dnstest_check_confirm_test.py
pydnstest/tests/dnstest_check_remove_test.py
pydnstest/tests/dnstest_check_rename_test.py
pydnstest/tests/dnstest_config_test.py
pydnstest/tests/dnstest_dns_test.py
pydnstest/tests/dnstest_inputline_test.py
pydnstest/tests/dnstest_main_test.py
pydnstest/tests/dnstest_parser_test.py
pydnstest/tests/dnstest_test.py
pydnstest/tests/dnstest_util_test.py
pydnstest-0.4.0.data/scripts/pydnstest
pydnstest-0.4.0.dist-info/DESCRIPTION.rst
pydnstest-0.4.0.dist-info/METADATA
pydnstest-0.4.0.dist-info/RECORD
pydnstest-0.4.0.dist-info/WHEEL
pydnstest-0.4.0.dist-info/metadata.json
pydnstest-0.4.0.dist-info/top_level.txt
