Metadata-Version: 2.0
Name: pydnstest
Version: 0.4.0
Summary: Tool to test DNS changes on a staging server and verify in production
Home-page: http://github.com/jantman/pydnstest/
Author: Jason Antman
Author-email: jason@jasonantman.com
License: AGPLv3+
Keywords: dns testing pydns
Platform: UNKNOWN
Classifier: Development Status :: 4 - Beta
Classifier: Environment :: Console
Classifier: Intended Audience :: System Administrators
Classifier: Intended Audience :: Information Technology
Classifier: License :: OSI Approved :: GNU Affero General Public License v3 or later (AGPLv3+)
Classifier: Natural Language :: English
Classifier: Operating System :: POSIX
Classifier: Programming Language :: Python
Classifier: Programming Language :: Python :: 2.7
Classifier: Programming Language :: Python :: 3.4
Classifier: Programming Language :: Python :: 3.5
Classifier: Programming Language :: Python :: 3.6
Classifier: Topic :: Internet :: Name Service (DNS)
Requires-Dist: py3dns (==3.0.4)
Requires-Dist: pyparsing (==2.0.1)
